winzy_visual_notify/__init__.py
winzy_visual_notify/pyside6_speech_bubble.py
winzy_visual_notify/assets/bee.png
winzy_visual_notify/assets/dog.png
winzy_visual_notify/assets/dog2.png
winzy_visual_notify/assets/ghost.png
winzy_visual_notify/assets/hen.png
winzy_visual_notify/assets/man.png
winzy_visual_notify/assets/pear.png
winzy_visual_notify/assets/purple.png
winzy_visual_notify/assets/watermellon.png
winzy_visual_notify-0.0.4.dist-info/licenses/LICENSE
winzy_visual_notify-0.0.4.dist-info/METADATA
winzy_visual_notify-0.0.4.dist-info/WHEEL
winzy_visual_notify-0.0.4.dist-info/entry_points.txt
winzy_visual_notify-0.0.4.dist-info/top_level.txt
winzy_visual_notify-0.0.4.dist-info/RECORD
