Metadata-Version: 2.4
Name: winzy-visual-notify
Version: 0.0.4
Summary: Notify using visual artefacts like clippy and other things.
Author: Sukhbinder Singh
License: Apache-2.0
Project-URL: Homepage, https://github.com/sukhbinder/winzy-visual-notify
Project-URL: Changelog, https://github.com/sukhbinder/winzy-visual-notify/releases
Project-URL: Issues, https://github.com/sukhbinder/winzy-visual-notify/issues
Project-URL: CI, https://github.com/sukhbinder/winzy-visual-notify/actions
Classifier: License :: OSI Approved :: Apache Software License
License-File: LICENSE
Requires-Dist: winzy
Requires-Dist: pyside6
Provides-Extra: test
Requires-Dist: pytest; extra == "test"
Dynamic: license-file
